filum_utils/__init__.py
filum_utils/config.py
filum_utils/enums.py
filum_utils/errors.py
filum_utils/sentry.py
filum_utils/clients/__init__.py
filum_utils/clients/action.py
filum_utils/clients/analytics.py
filum_utils/clients/common.py
filum_utils/clients/connection.py
filum_utils/clients/filum.py
filum_utils/clients/google.py
filum_utils/clients/iam.py
filum_utils/clients/log.py
filum_utils/clients/mini_app.py
filum_utils/clients/notification.py
filum_utils/clients/segment.py
filum_utils/clients/subscription.py
filum_utils/clients/contact_center/__init__.py
filum_utils/clients/contact_center/common.py
filum_utils/clients/contact_center/conversation.py
filum_utils/clients/contact_center/document.py
filum_utils/clients/contact_center/enums.py
filum_utils/clients/contact_center/types.py
filum_utils/clients/knowledge_base/__init__.py
filum_utils/clients/knowledge_base/client.py
filum_utils/clients/knowledge_base/enums.py
filum_utils/clients/knowledge_base/types.py
filum_utils/services/__init__.py
filum_utils/services/file.py
filum_utils/services/subscription/__init__.py
filum_utils/services/subscription/automated_action.py
filum_utils/services/subscription/base_campaign.py
filum_utils/services/subscription/campaign.py
filum_utils/services/subscription/engagement_campaign.py
filum_utils/types/__init__.py
filum_utils/types/account.py
filum_utils/types/action.py
filum_utils/types/automated_action.py
filum_utils/types/campaign.py
filum_utils/types/common.py
filum_utils/types/engagement_campaign.py
filum_utils/types/engagement_message.py
filum_utils/types/mini_app.py
filum_utils/types/organization.py
filum_utils/types/segment.py
filum_utils/types/subscription.py
filum_utils/types/survey.py
filum_utils/types/survey_response.py
filum_utils/utils/__init__.py
filum_utils/utils/datetime_formatter.py
filum_utils/utils/segment_users.py
filum_utils/utils/smart_distributions.py
filum_utils/utils/string_formatter.py
filum_utils/utils/automated_action/__init__.py
filum_utils-0.1.64.dist-info/METADATA
filum_utils-0.1.64.dist-info/WHEEL
filum_utils-0.1.64.dist-info/top_level.txt
filum_utils-0.1.64.dist-info/RECORD
