Metadata-Version: 2.4
Name: filum-utils
Version: 0.1.64
Summary: Filum Utils
Author: Hiep Nguyen
Author-email: <hnguyen@filum.ai>
Classifier: Development Status :: 3 - Alpha
Classifier: Intended Audience :: Developers
Classifier: Programming Language :: Python :: 2
Classifier: Programming Language :: Python :: 3
Classifier: Operating System :: OS Independent
Requires-Dist: requests==2.31.0
Requires-Dist: sentry-sdk[fastapi]==1.30.0
Requires-Dist: filum-analytics-python==1.1.1
Requires-Dist: glom==20.11.0
Requires-Dist: pyexcel==0.7.0
Requires-Dist: pyexcel-xls==0.7.0
Requires-Dist: pyexcel-xlsx==0.6.0
Requires-Dist: openpyxl==3.0.10
Requires-Dist: setuptools==68.0.0
Requires-Dist: tenacity==8.2.3
Requires-Dist: python-dateutil>=2.8.1
Requires-Dist: google-cloud-pubsub==2.13.6
Requires-Dist: google-cloud-storage==2.5.0
Dynamic: author
Dynamic: author-email
Dynamic: classifier
Dynamic: description
Dynamic: requires-dist
Dynamic: summary
